Workbook

Sheet CREDITO_FINANCEIRO
A1: Proposta de Referência | B1: Status da Proposta | C1: CNES | D1: Entidade | E1: CNPJ | F1: UF | G1: Município | H1: Dt. Cadastro | I1: Dt. Atualização | J1: Dívida Aprox. | K1: VL_SALDO_DEVEDOR | L1: VL_TRIBUTO_FEDERAL_ESTIMADO | M1: CANCELAR
M2: =IFERROR(IF(VLOOKUP(Tabela1[[#This Row],[Proposta de Referência]],'CCPP-CANCELAR'!B$2:G$1048576,2,FALSE)<>"","CANCELAR_PROPOSTA",""),"")
M3: =IFERROR(IF(VLOOKUP(Tabela1[[#This Row],[Proposta de Referência]],'CCPP-CANCELAR'!B$2:G$1048576,2,FALSE)<>"","CANCELAR_PROPOSTA",""),"")
M4: =IFERROR(IF(VLOOKUP(Tabela1[[#This Row],[Proposta de Referência]],'CCPP-CANCELAR'!B$2:G$1048576,2,FALSE)<>"","CANCELAR_PROPOSTA",""),"")
M5: =IFERROR(IF(VLOOKUP(Tabela1[[#This Row],[Proposta de Referência]],'CCPP-CANCELAR'!B$2:G$1048576,2,FALSE)<>"","CANCELAR_PROPOSTA",""),"")
M6: =IFERROR(IF(VLOOKUP(Tabela1[[#This Row],[Proposta de Referência]],'CCPP-CANCELAR'!B$2:G$1048576,2,FALSE)<>"","CANCELAR_PROPOSTA",""),"")
M7: =IFERROR(IF(VLOOKUP(Tabela1[[#This Row],[Proposta de Referência]],'CCPP-CANCELAR'!B$2:G$1048576,2,FALSE)<>"","CANCELAR_PROPOSTA",""),"")
M8: =IFERROR(IF(VLOOKUP(Tabela1[[#This Row],[Proposta de Referência]],'CCPP-CANCELAR'!B$2:G$1048576,2,FALSE)<>"","CANCELAR_PROPOSTA",""),"")
M9: =IFERROR(IF(VLOOKUP(Tabela1[[#This Row],[Proposta de Referência]],'CCPP-CANCELAR'!B$2:G$1048576,2,FALSE)<>"","CANCELAR_PROPOSTA",""),"")
M10: =IFERROR(IF(VLOOKUP(Tabela1[[#This Row],[Proposta de Referência]],'CCPP-CANCELAR'!B$2:G$1048576,2,FALSE)<>"","CANCELAR_PROPOSTA",""),"")
M11: =IFERROR(IF(VLOOKUP(Tabela1[[#This Row],[Proposta de Referência]],'CCPP-CANCELAR'!B$2:G$1048576,2,FALSE)<>"","CANCELAR_PROPOSTA",""),"")
M12: =IFERROR(IF(VLOOKUP(Tabela1[[#This Row],[Proposta de Referência]],'CCPP-CANCELAR'!B$2:G$1048576,2,FALSE)<>"","CANCELAR_PROPOSTA",""),"")
M13: =IFERROR(IF(VLOOKUP(Tabela1[[#This Row],[Proposta de Referência]],'CCPP-CANCELAR'!B$2:G$1048576,2,FALSE)<>"","CANCELAR_PROPOSTA",""),"")
... M500: =IFERROR(IF(VLOOKUP(Tabela1[[#This Row],[Proposta de Referência]],'CCPP-CANCELAR'!B$2:G$1048576,2,FALSE)<>"","CANCELAR_PROPOSTA",""),"")

Sheet INFO
B1: MONITORAMENTO DE COMPONENTE-
B2: DEEQAE - Departamento de Estratégias para a Expansão e Qualificação da Atenção Especializada | G2: Data - hora do levatamento: | H2: 04/08/2025 14:15
B3: COQAE - Coordenação de Gestão da Informação da Expansão e Qualificação da Atenção Especializada
B5: Aba "INFO" — Guia de Navegação do PLANILHÃO
B6: 🎨 Aba/Cor | C6: 📌 Conteúdo | D6: 📍 Fonte | E6: 🗓️ Período | F6: 🚧 Frequência | G6: 🔍 Observações | H6: ✨ Limitações
B7: VISÃO GERAL – CRÉDITO FINANCEIRO (VISÃO_GERAL) | C7: Visão consolidada das propostas de Crédito Financeiro, com fórmulas de análise matemática. Integra dados de cancelamento de propostas e dívidas hospitalares. | D7: InvestSUS + DEEQAE/CGPPQAE | E7: =$H$2 -> 04/08/2025 14:15 | F7: Diária | G7: Avaliação em duas etapas: (1) Verificar se a matriz de oferta ultrapassa R$ 100 mil (Art. 7º); (2) Verificar se a dívida estimada atende aos critérios do Art. 8º. | H7: Não detalha OCI e componentes cirúrgicos; consultar abas M_OFERTA_CF_CC e M_OFERTA_CF_OCI.
B8: SIMPLIFICADO – CRÉDITO FINANCEIRO (SIMP_CF) | C8: Visão simplificada das proposta de Crédito Financeiro, com fórmulas de análise matemática. Integra dados de cancelamento de propostas. APOIO | D8: InvestSUS + DEEQAE/CGPPQAE | E8: =$H$2 -> 04/08/2025 14:15 | F8: Diária | G8: Uma visão SIMPLIFICADA do Credito Financeiro para o APOIO | H8: Não detalha OCI e componentes cirúrgicos; consultar abas M_OFERTA_CF_CC e M_OFERTA_CF_OCI.
B9: MATRIZ DE OFERTA – CRÉDITO FINANCEIRO – CIRURGIAS (M_OFERTA_CF_CC) | C9: Detalhamento das propostas cirúrgicas: UF, Município, CNES, Entidade, Procedimentos SIGTAP, valores SUS, complementações, estimativas mensais. | D9: InvestSUS | E9: =$H$2 -> 04/08/2025 14:15 | F9: Diária | G9: Cruzamento entre Crédito Financeiro e TB_PROCEDIMENTO. Estimativa mensal calculada por proposta. | H9: Abrange apenas o componente cirúrgico.
B10: MATRIZ DE OFERTA – CRÉDITO FINANCEIRO – OCI (M_OFERTA_CF_OCI) | C10: Detalhamento das propostas OCI: UF, Município, CNES, Entidade, Procedimentos, valores unitários e totais mensais. | D10: InvestSUS | E10: =$H$2 -> 04/08/2025 14:15 | F10: Diária | G10: Cruzamento entre Crédito Financeiro e TB_OCI. Estimativa mensal calculada por proposta. | H10: Abrange apenas o componente OCI.
B11: VISÃO GERAL – MODALIDADE 1 (VISÃO_GERAL) | C11: Visão consolidada das propostas da Modalidade 1, com fórmulas de análise matemática. Integra dados de cancelamento de propostas e dívidas hospitalares. | D11: InvestSUS + DEEQAE/CGPPQAE | E11: =$H$2 -> 04/08/2025 14:15 | F11: Diária | G11: Avaliação em duas etapas: (1) Verificar se a matriz de oferta ultrapassa R$ 100 mil (Art. 7º); | H11: Não detalha OCI e componentes cirúrgicos; consultar abas M_OFERTA_M1_CC e M_OFERTA_M1_OCI.
B12: SIMPLIFICADO – MODALIDADE 1 (SIMP_M1) | C12: Visão simplificada das proposta da Modalidade 1, com fórmulas de análise matemática. Integra dados de cancelamento de propostas. APOIO | D12: InvestSUS + DEEQAE/CGPPQAE | E12: =$H$2 -> 04/08/2025 14:15 | F12: Diária | G12: Uma visão SIMPLIFICADA do Credito Financeiro para o APOIO | H12: Não detalha OCI e componentes cirúrgicos; consultar abas M_OFERTA_CF_CC e M_OFERTA_CF_OCI.
B13: MATRIZ DE OFERTA – MODALIDADE 1 – CIRURGIAS (M_OFERTA_M1_CC) | C13: Detalhamento das propostas cirúrgicas da Modalidade 1: UF, Município, CNES, Entidade, Procedimentos SIGTAP, valores SUS, complementações, estimativas mensais. | D13: InvestSUS | E13: =$H$2 -> 04/08/2025 14:15 | F13: Diária | G13: Cruzamento entre Modalidade 1 e TB_PROCEDIMENTO. Estimativa mensal calculada por proposta. | H13: Abrange apenas componente cirúrgico da Modalidade 1.
B14: MATRIZ DE OFERTA – MODALIDADE 1 – OCI (M_OFERTA_M1_OCI) | C14: Detalhamento das propostas OCI da Modalidade 1: UF, Município, CNES, Entidade, Procedimentos, valores unitários e totais mensais. | D14: InvestSUS | E14: =$H$2 -> 04/08/2025 14:15 | F14: Diária | G14: Cruzamento entre Modalidade 1 e TB_OCI. Estimativa mensal calculada por proposta. | H14: Abrange apenas componente OCI da Modalidade 1.
B15: SOLICITAÇÃO DE CANCELAMENTO DE PROPOSTAS (CCPP-CANCELAR) | C15: Lista de propostas canceladas pela CGPPQAE, mas ainda constam como aprovadas no InvestSUS. | D15: DEEQAE – CGPPQAE | E15: =$H$2 -> 04/08/2025 14:15 | F15: Diária | G15: Elaborada manualmente pela equipe técnica. Pode haver divergência entre status oficial e status no InvestSUS. | H15: Dados podem não refletir o status real no sistema InvestSUS.
B16: LISTA DE ENTIDADES COM DÍVIDA ATIVA (HOSPITAIS_COM_DIVIDAS) | C16: Relação de entidades hospitalares com pendências fiscais (FGTS e LC110), classificadas por CNAE e esfera federativa. | D16: — | E16: =$H$2 -> 04/08/2025 14:15 | F16: Diária | G16: Filtro aplicado: Tipo de inscrição ≠ FGTS/LC110; CNAE = atendimento hospitalar; Esfera federativa = "Não se aplica". | H16: Dados sujeitos a atualização conforme registros fiscais.
B18: obs | C18: possui 6 abas ocultas das planilhas presente no sitehttps://investsuspaineis.saude.gov.br/extensions/CGIN_PMAE/CGIN_PMAE.html#
B21: Atualizações
B22: MODALIDADE 1 - correção da aba VISÃO_GERAL_M1 - acrescimo de linhas na tabela.
G23: VERSÃO | H23: 2.5
XFC1048575: '@OTAVIOAUGUST

Sheet VISÃO_GERAL
A1: TOTAL | B1: =(SUMPRODUCT(1/COUNTIF(B3:B6690,B3:B6690&"")))-1 -> 1 | G1: =(SUMPRODUCT(1/COUNTIF(G3:G6690,G3:G6690&"")))-1 -> 1 | H1: =(SUMPRODUCT(1/COUNTIF(H3:H6690,H3:H6690&"")))-1 -> 1 | I1: =SUBTOTAL(109,I3:I1048576) -> #N/A | J1: =SUBTOTAL(109,J3:J1048576) -> #N/A | K1: =SUBTOTAL(109,K3:K1048576) -> #N/A | L1: =SUBTOTAL(109,L3:L1048576) -> #N/A | N1: =SUBTOTAL(109,N3:N1048576) -> #N/A | O1: =SUBTOTAL(109,O3:O1048576) -> #N/A | P1: =SUBTOTAL(109,P3:P1048576) -> #N/A | Q1: =SUBTOTAL(109,Q3:Q1048576) -> #N/A | T1: =SUBTOTAL(109,T3:T1048576) -> #N/A | U1: =SUBTOTAL(109,U3:U1048576) -> #N/A | X1: =SUBTOTAL(109,X3:X1048576) -> 0
A2: Status da Proposta - DEEQAE | B2: Proposta de Referência | C2: Status da Proposta | D2: CNPJ | E2: CNES | F2: Entidade | G2: UF | H2: Município | I2: Dívida Aprox. | J2: VL_SALDO_DEVEDOR | K2: VL_TRIBUTO_FEDERAL ESTIMADO | L2: TRAZER O VALOR MAIOR ENTRE SALDO DEVEDOR E TRIBUTO FEDERAL | M2: POSSUI VALOR PARA O CREDITO | N2: VL_OFERTA_OCI MÊS | O2: VL_OFERTA_COMP_CIRUR MÊS | P2: VALOR SOMADO DAS OFERTAS MÊS | Q2: VALOR SOMADO DAS OFERTAS POR ANO | R2: 1ª análise - verificar se a matriz de oferta está acima de 100mil - art.7º; | S2: QUAL FAIXA DA DIVIDA | T2: VL_FAIXA DA DIVIDA CONFORME TRIBUTO FEDERAL ESTIMADO | U2: DIFERENÇA ENTRE A DIVIDA ESTIMADA X VALOR OFERTA | V2: 2ª análise - verificar se o valor da dívida estimada está dentro dos critérios do art. 8° | W2: CNPJ CURTO | X2: DIVIDA HOSPITAL POR CNPJ
A3: =IFERROR((Tabela4[[#This Row],[Status da Proposta]]),"") | B3: =IFERROR((CREDITO_FINANCEIRO!A3),"") -> 0 | C3: =IFERROR((VLOOKUP(B3,CREDITO_FINANCEIRO!A:B,2,FALSE)),"") | D3: =IFERROR((VLOOKUP(B3,CREDITO_FINANCEIRO!A:E,5,FALSE)),"") | E3: =IFERROR((VLOOKUP(B3,CREDITO_FINANCEIRO!A:C,3,FALSE)),"") | F3: =IFERROR((VLOOKUP(B3,CREDITO_FINANCEIRO!A:G,4,FALSE)),"") | G3: =VLOOKUP(B3,CREDITO_FINANCEIRO!A:G,6,FALSE) -> #N/A | H3: =VLOOKUP(B3,CREDITO_FINANCEIRO!A:G,7,FALSE) -> #N/A | I3: =VLOOKUP(B3,CREDITO_FINANCEIRO!A:K,10,FALSE) -> #N/A | J3: =VLOOKUP(B3,CREDITO_FINANCEIRO!A:K,11,FALSE) -> #N/A | K3: =VLOOKUP(B3,CREDITO_FINANCEIRO!A:L,12,FALSE) -> #N/A | L3: =MAX(I3:K3) -> #N/A | M3: =IF(((L3)=0),"NÃO, POSSUI VALOR","SIM, POSSUI VALOR") -> #N/A | N3: =VLOOKUP(Tabela4[[#This Row],[Proposta de Referência]],SIMP_CF!A:K,9,FALSE) -> #N/A | O3: =VLOOKUP(Tabela4[[#This Row],[Proposta de Referência]],SIMP_CF!A:K,8,FALSE) -> #N/A | P3: =O3+N3 -> #N/A | Q3: =P3*12 -> #N/A | R3: =IF(P3>=100000,"SIM, POSSUI VALOR ACIMA DE R$100.000,00","NÃO, POSSUI VALOR NECESSÁRIO") -> #N/A | S3: =IF(L3>10000000,"Faixa I - 30%",IF(L3>=5000000,"Faixa II - 40%","Faixa III - 50%")) -> #N/A | T3: =IF(L3>10000000,L3*0.3,IF(L3>=5000000,L3*0.4,L3*0.5)) -> #N/A | U3: =T3-P3 -> #N/A | V3: =IF(OR(U3>=T3,U3<0,T3=0),"NÃO, ATENDEU O CRITÉRIO","SIM, ATENDEU O CRITÉRIO") -> #N/A | W3: =LEFT(D3,8) | X3: =IFERROR(VLOOKUP(W3,HOSPITAIS_COM_DIVIDAS!A:E,5,FALSE),"")
A4: =IFERROR((Tabela4[[#This Row],[Status da Proposta]]),"") | B4: =IFERROR((CREDITO_FINANCEIRO!A4),"") -> 0 | C4: =IFERROR((VLOOKUP(B4,CREDITO_FINANCEIRO!A:B,2,FALSE)),"") | D4: =IFERROR((VLOOKUP(B4,CREDITO_FINANCEIRO!A:E,5,FALSE)),"") | E4: =IFERROR((VLOOKUP(B4,CREDITO_FINANCEIRO!A:C,3,FALSE)),"") | F4: =IFERROR((VLOOKUP(B4,CREDITO_FINANCEIRO!A:G,4,FALSE)),"") | G4: =VLOOKUP(B4,CREDITO_FINANCEIRO!A:G,6,FALSE) -> #N/A | H4: =VLOOKUP(B4,CREDITO_FINANCEIRO!A:G,7,FALSE) -> #N/A | I4: =VLOOKUP(B4,CREDITO_FINANCEIRO!A:K,10,FALSE) -> #N/A | J4: =VLOOKUP(B4,CREDITO_FINANCEIRO!A:K,11,FALSE) -> #N/A | K4: =VLOOKUP(B4,CREDITO_FINANCEIRO!A:L,12,FALSE) -> #N/A | L4: =MAX(I4:K4) -> #N/A | M4: =IF(((L4)=0),"NÃO, POSSUI VALOR","SIM, POSSUI VALOR") -> #N/A | N4: =VLOOKUP(Tabela4[[#This Row],[Proposta de Referência]],SIMP_CF!A:K,9,FALSE) -> #N/A | O4: =VLOOKUP(Tabela4[[#This Row],[Proposta de Referência]],SIMP_CF!A:K,8,FALSE) -> #N/A | P4: =O4+N4 -> #N/A | Q4: =P4*12 -> #N/A | R4: =IF(P4>=100000,"SIM, POSSUI VALOR ACIMA DE R$100.000,00","NÃO, POSSUI VALOR NECESSÁRIO") -> #N/A | S4: =IF(L4>10000000,"Faixa I - 30%",IF(L4>=5000000,"Faixa II - 40%","Faixa III - 50%")) -> #N/A | T4: =IF(L4>10000000,L4*0.3,IF(L4>=5000000,L4*0.4,L4*0.5)) -> #N/A | U4: =T4-P4 -> #N/A | V4: =IF(OR(U4>=T4,U4<0,T4=0),"NÃO, ATENDEU O CRITÉRIO","SIM, ATENDEU O CRITÉRIO") -> #N/A | W4: =LEFT(D4,8) | X4: =IFERROR(VLOOKUP(W4,HOSPITAIS_COM_DIVIDAS!A:E,5,FALSE),"")
A5: =IFERROR((Tabela4[[#This Row],[Status da Proposta]]),"") | B5: =IFERROR((CREDITO_FINANCEIRO!A5),"") -> 0 | C5: =IFERROR((VLOOKUP(B5,CREDITO_FINANCEIRO!A:B,2,FALSE)),"") | D5: =IFERROR((VLOOKUP(B5,CREDITO_FINANCEIRO!A:E,5,FALSE)),"") | E5: =IFERROR((VLOOKUP(B5,CREDITO_FINANCEIRO!A:C,3,FALSE)),"") | F5: =IFERROR((VLOOKUP(B5,CREDITO_FINANCEIRO!A:G,4,FALSE)),"") | G5: =VLOOKUP(B5,CREDITO_FINANCEIRO!A:G,6,FALSE) -> #N/A | H5: =VLOOKUP(B5,CREDITO_FINANCEIRO!A:G,7,FALSE) -> #N/A | I5: =VLOOKUP(B5,CREDITO_FINANCEIRO!A:K,10,FALSE) -> #N/A | J5: =VLOOKUP(B5,CREDITO_FINANCEIRO!A:K,11,FALSE) -> #N/A | K5: =VLOOKUP(B5,CREDITO_FINANCEIRO!A:L,12,FALSE) -> #N/A | L5: =MAX(I5:K5) -> #N/A | M5: =IF(((L5)=0),"NÃO, POSSUI VALOR","SIM, POSSUI VALOR") -> #N/A | N5: =VLOOKUP(Tabela4[[#This Row],[Proposta de Referência]],SIMP_CF!A:K,9,FALSE) -> #N/A | O5: =VLOOKUP(Tabela4[[#This Row],[Proposta de Referência]],SIMP_CF!A:K,8,FALSE) -> #N/A | P5: =O5+N5 -> #N/A | Q5: =P5*12 -> #N/A | R5: =IF(P5>=100000,"SIM, POSSUI VALOR ACIMA DE R$100.000,00","NÃO, POSSUI VALOR NECESSÁRIO") -> #N/A | S5: =IF(L5>10000000,"Faixa I - 30%",IF(L5>=5000000,"Faixa II - 40%","Faixa III - 50%")) -> #N/A | T5: =IF(L5>10000000,L5*0.3,IF(L5>=5000000,L5*0.4,L5*0.5)) -> #N/A | U5: =T5-P5 -> #N/A | V5: =IF(OR(U5>=T5,U5<0,T5=0),"NÃO, ATENDEU O CRITÉRIO","SIM, ATENDEU O CRITÉRIO") -> #N/A | W5: =LEFT(D5,8) | X5: =IFERROR(VLOOKUP(W5,HOSPITAIS_COM_DIVIDAS!A:E,5,FALSE),"")
A6: =IFERROR((Tabela4[[#This Row],[Status da Proposta]]),"") | B6: =IFERROR((CREDITO_FINANCEIRO!A6),"") -> 0 | C6: =IFERROR((VLOOKUP(B6,CREDITO_FINANCEIRO!A:B,2,FALSE)),"") | D6: =IFERROR((VLOOKUP(B6,CREDITO_FINANCEIRO!A:E,5,FALSE)),"") | E6: =IFERROR((VLOOKUP(B6,CREDITO_FINANCEIRO!A:C,3,FALSE)),"") | F6: =IFERROR((VLOOKUP(B6,CREDITO_FINANCEIRO!A:G,4,FALSE)),"") | G6: =VLOOKUP(B6,CREDITO_FINANCEIRO!A:G,6,FALSE) -> #N/A | H6: =VLOOKUP(B6,CREDITO_FINANCEIRO!A:G,7,FALSE) -> #N/A | I6: =VLOOKUP(B6,CREDITO_FINANCEIRO!A:K,10,FALSE) -> #N/A | J6: =VLOOKUP(B6,CREDITO_FINANCEIRO!A:K,11,FALSE) -> #N/A | K6: =VLOOKUP(B6,CREDITO_FINANCEIRO!A:L,12,FALSE) -> #N/A | L6: =MAX(I6:K6) -> #N/A | M6: =IF(((L6)=0),"NÃO, POSSUI VALOR","SIM, POSSUI VALOR") -> #N/A | N6: =VLOOKUP(Tabela4[[#This Row],[Proposta de Referência]],SIMP_CF!A:K,9,FALSE) -> #N/A | O6: =VLOOKUP(Tabela4[[#This Row],[Proposta de Referência]],SIMP_CF!A:K,8,FALSE) -> #N/A | P6: =O6+N6 -> #N/A | Q6: =P6*12 -> #N/A | R6: =IF(P6>=100000,"SIM, POSSUI VALOR ACIMA DE R$100.000,00","NÃO, POSSUI VALOR NECESSÁRIO") -> #N/A | S6: =IF(L6>10000000,"Faixa I - 30%",IF(L6>=5000000,"Faixa II - 40%","Faixa III - 50%")) -> #N/A | T6: =IF(L6>10000000,L6*0.3,IF(L6>=5000000,L6*0.4,L6*0.5)) -> #N/A | U6: =T6-P6 -> #N/A | V6: =IF(OR(U6>=T6,U6<0,T6=0),"NÃO, ATENDEU O CRITÉRIO","SIM, ATENDEU O CRITÉRIO") -> #N/A | W6: =LEFT(D6,8) | X6: =IFERROR(VLOOKUP(W6,HOSPITAIS_COM_DIVIDAS!A:E,5,FALSE),"")
A7: =IFERROR((Tabela4[[#This Row],[Status da Proposta]]),"") | B7: =IFERROR((CREDITO_FINANCEIRO!A7),"") -> 0 | C7: =IFERROR((VLOOKUP(B7,CREDITO_FINANCEIRO!A:B,2,FALSE)),"") | D7: =IFERROR((VLOOKUP(B7,CREDITO_FINANCEIRO!A:E,5,FALSE)),"") | E7: =IFERROR((VLOOKUP(B7,CREDITO_FINANCEIRO!A:C,3,FALSE)),"") | F7: =IFERROR((VLOOKUP(B7,CREDITO_FINANCEIRO!A:G,4,FALSE)),"") | G7: =VLOOKUP(B7,CREDITO_FINANCEIRO!A:G,6,FALSE) -> #N/A | H7: =VLOOKUP(B7,CREDITO_FINANCEIRO!A:G,7,FALSE) -> #N/A | I7: =VLOOKUP(B7,CREDITO_FINANCEIRO!A:K,10,FALSE) -> #N/A | J7: =VLOOKUP(B7,CREDITO_FINANCEIRO!A:K,11,FALSE) -> #N/A | K7: =VLOOKUP(B7,CREDITO_FINANCEIRO!A:L,12,FALSE) -> #N/A | L7: =MAX(I7:K7) -> #N/A | M7: =IF(((L7)=0),"NÃO, POSSUI VALOR","SIM, POSSUI VALOR") -> #N/A | N7: =VLOOKUP(Tabela4[[#This Row],[Proposta de Referência]],SIMP_CF!A:K,9,FALSE) -> #N/A | O7: =VLOOKUP(Tabela4[[#This Row],[Proposta de Referência]],SIMP_CF!A:K,8,FALSE) -> #N/A | P7: =O7+N7 -> #N/A | Q7: =P7*12 -> #N/A | R7: =IF(P7>=100000,"SIM, POSSUI VALOR ACIMA DE R$100.000,00","NÃO, POSSUI VALOR NECESSÁRIO") -> #N/A | S7: =IF(L7>10000000,"Faixa I - 30%",IF(L7>=5000000,"Faixa II - 40%","Faixa III - 50%")) -> #N/A | T7: =IF(L7>10000000,L7*0.3,IF(L7>=5000000,L7*0.4,L7*0.5)) -> #N/A | U7: =T7-P7 -> #N/A | V7: =IF(OR(U7>=T7,U7<0,T7=0),"NÃO, ATENDEU O CRITÉRIO","SIM, ATENDEU O CRITÉRIO") -> #N/A | W7: =LEFT(D7,8) | X7: =IFERROR(VLOOKUP(W7,HOSPITAIS_COM_DIVIDAS!A:E,5,FALSE),"")
A8: =IFERROR((Tabela4[[#This Row],[Status da Proposta]]),"") | B8: =IFERROR((CREDITO_FINANCEIRO!A8),"") -> 0 | C8: =IFERROR((VLOOKUP(B8,CREDITO_FINANCEIRO!A:B,2,FALSE)),"") | D8: =IFERROR((VLOOKUP(B8,CREDITO_FINANCEIRO!A:E,5,FALSE)),"") | E8: =IFERROR((VLOOKUP(B8,CREDITO_FINANCEIRO!A:C,3,FALSE)),"") | F8: =IFERROR((VLOOKUP(B8,CREDITO_FINANCEIRO!A:G,4,FALSE)),"") | G8: =VLOOKUP(B8,CREDITO_FINANCEIRO!A:G,6,FALSE) -> #N/A | H8: =VLOOKUP(B8,CREDITO_FINANCEIRO!A:G,7,FALSE) -> #N/A | I8: =VLOOKUP(B8,CREDITO_FINANCEIRO!A:K,10,FALSE) -> #N/A | J8: =VLOOKUP(B8,CREDITO_FINANCEIRO!A:K,11,FALSE) -> #N/A | K8: =VLOOKUP(B8,CREDITO_FINANCEIRO!A:L,12,FALSE) -> #N/A | L8: =MAX(I8:K8) -> #N/A | M8: =IF(((L8)=0),"NÃO, POSSUI VALOR","SIM, POSSUI VALOR") -> #N/A | N8: =VLOOKUP(Tabela4[[#This Row],[Proposta de Referência]],SIMP_CF!A:K,9,FALSE) -> #N/A | O8: =VLOOKUP(Tabela4[[#This Row],[Proposta de Referência]],SIMP_CF!A:K,8,FALSE) -> #N/A | P8: =O8+N8 -> #N/A | Q8: =P8*12 -> #N/A | R8: =IF(P8>=100000,"SIM, POSSUI VALOR ACIMA DE R$100.000,00","NÃO, POSSUI VALOR NECESSÁRIO") -> #N/A | S8: =IF(L8>10000000,"Faixa I - 30%",IF(L8>=5000000,"Faixa II - 40%","Faixa III - 50%")) -> #N/A | T8: =IF(L8>10000000,L8*0.3,IF(L8>=5000000,L8*0.4,L8*0.5)) -> #N/A | U8: =T8-P8 -> #N/A | V8: =IF(OR(U8>=T8,U8<0,T8=0),"NÃO, ATENDEU O CRITÉRIO","SIM, ATENDEU O CRITÉRIO") -> #N/A | W8: =LEFT(D8,8) | X8: =IFERROR(VLOOKUP(W8,HOSPITAIS_COM_DIVIDAS!A:E,5,FALSE),"")
A9: =IFERROR((Tabela4[[#This Row],[Status da Proposta]]),"") | B9: =IFERROR((CREDITO_FINANCEIRO!A9),"") -> 0 | C9: =IFERROR((VLOOKUP(B9,CREDITO_FINANCEIRO!A:B,2,FALSE)),"") | D9: =IFERROR((VLOOKUP(B9,CREDITO_FINANCEIRO!A:E,5,FALSE)),"") | E9: =IFERROR((VLOOKUP(B9,CREDITO_FINANCEIRO!A:C,3,FALSE)),"") | F9: =IFERROR((VLOOKUP(B9,CREDITO_FINANCEIRO!A:G,4,FALSE)),"") | G9: =VLOOKUP(B9,CREDITO_FINANCEIRO!A:G,6,FALSE) -> #N/A | H9: =VLOOKUP(B9,CREDITO_FINANCEIRO!A:G,7,FALSE) -> #N/A | I9: =VLOOKUP(B9,CREDITO_FINANCEIRO!A:K,10,FALSE) -> #N/A | J9: =VLOOKUP(B9,CREDITO_FINANCEIRO!A:K,11,FALSE) -> #N/A | K9: =VLOOKUP(B9,CREDITO_FINANCEIRO!A:L,12,FALSE) -> #N/A | L9: =MAX(I9:K9) -> #N/A | M9: =IF(((L9)=0),"NÃO, POSSUI VALOR","SIM, POSSUI VALOR") -> #N/A | N9: =VLOOKUP(Tabela4[[#This Row],[Proposta de Referência]],SIMP_CF!A:K,9,FALSE) -> #N/A | O9: =VLOOKUP(Tabela4[[#This Row],[Proposta de Referência]],SIMP_CF!A:K,8,FALSE) -> #N/A | P9: =O9+N9 -> #N/A | Q9: =P9*12 -> #N/A | R9: =IF(P9>=100000,"SIM, POSSUI VALOR ACIMA DE R$100.000,00","NÃO, POSSUI VALOR NECESSÁRIO") -> #N/A | S9: =IF(L9>10000000,"Faixa I - 30%",IF(L9>=5000000,"Faixa II - 40%","Faixa III - 50%")) -> #N/A | T9: =IF(L9>10000000,L9*0.3,IF(L9>=5000000,L9*0.4,L9*0.5)) -> #N/A | U9: =T9-P9 -> #N/A | V9: =IF(OR(U9>=T9,U9<0,T9=0),"NÃO, ATENDEU O CRITÉRIO","SIM, ATENDEU O CRITÉRIO") -> #N/A | W9: =LEFT(D9,8) | X9: =IFERROR(VLOOKUP(W9,HOSPITAIS_COM_DIVIDAS!A:E,5,FALSE),"")
A10: =IFERROR((Tabela4[[#This Row],[Status da Proposta]]),"") | B10: =IFERROR((CREDITO_FINANCEIRO!A10),"") -> 0 | C10: =IFERROR((VLOOKUP(B10,CREDITO_FINANCEIRO!A:B,2,FALSE)),"") | D10: =IFERROR((VLOOKUP(B10,CREDITO_FINANCEIRO!A:E,5,FALSE)),"") | E10: =IFERROR((VLOOKUP(B10,CREDITO_FINANCEIRO!A:C,3,FALSE)),"") | F10: =IFERROR((VLOOKUP(B10,CREDITO_FINANCEIRO!A:G,4,FALSE)),"") | G10: =VLOOKUP(B10,CREDITO_FINANCEIRO!A:G,6,FALSE) -> #N/A | H10: =VLOOKUP(B10,CREDITO_FINANCEIRO!A:G,7,FALSE) -> #N/A | I10: =VLOOKUP(B10,CREDITO_FINANCEIRO!A:K,10,FALSE) -> #N/A | J10: =VLOOKUP(B10,CREDITO_FINANCEIRO!A:K,11,FALSE) -> #N/A | K10: =VLOOKUP(B10,CREDITO_FINANCEIRO!A:L,12,FALSE) -> #N/A | L10: =MAX(I10:K10) -> #N/A | M10: =IF(((L10)=0),"NÃO, POSSUI VALOR","SIM, POSSUI VALOR") -> #N/A | N10: =VLOOKUP(Tabela4[[#This Row],[Proposta de Referência]],SIMP_CF!A:K,9,FALSE) -> #N/A | O10: =VLOOKUP(Tabela4[[#This Row],[Proposta de Referência]],SIMP_CF!A:K,8,FALSE) -> #N/A | P10: =O10+N10 -> #N/A | Q10: =P10*12 -> #N/A | R10: =IF(P10>=100000,"SIM, POSSUI VALOR ACIMA DE R$100.000,00","NÃO, POSSUI VALOR NECESSÁRIO") -> #N/A | S10: =IF(L10>10000000,"Faixa I - 30%",IF(L10>=5000000,"Faixa II - 40%","Faixa III - 50%")) -> #N/A | T10: =IF(L10>10000000,L10*0.3,IF(L10>=5000000,L10*0.4,L10*0.5)) -> #N/A | U10: =T10-P10 -> #N/A | V10: =IF(OR(U10>=T10,U10<0,T10=0),"NÃO, ATENDEU O CRITÉRIO","SIM, ATENDEU O CRITÉRIO") -> #N/A | W10: =LEFT(D10,8) | X10: =IFERROR(VLOOKUP(W10,HOSPITAIS_COM_DIVIDAS!A:E,5,FALSE),"")
A11: =IFERROR((Tabela4[[#This Row],[Status da Proposta]]),"") | B11: =IFERROR((CREDITO_FINANCEIRO!A11),"") -> 0 | C11: =IFERROR((VLOOKUP(B11,CREDITO_FINANCEIRO!A:B,2,FALSE)),"") | D11: =IFERROR((VLOOKUP(B11,CREDITO_FINANCEIRO!A:E,5,FALSE)),"") | E11: =IFERROR((VLOOKUP(B11,CREDITO_FINANCEIRO!A:C,3,FALSE)),"") | F11: =IFERROR((VLOOKUP(B11,CREDITO_FINANCEIRO!A:G,4,FALSE)),"") | G11: =VLOOKUP(B11,CREDITO_FINANCEIRO!A:G,6,FALSE) -> #N/A | H11: =VLOOKUP(B11,CREDITO_FINANCEIRO!A:G,7,FALSE) -> #N/A | I11: =VLOOKUP(B11,CREDITO_FINANCEIRO!A:K,10,FALSE) -> #N/A | J11: =VLOOKUP(B11,CREDITO_FINANCEIRO!A:K,11,FALSE) -> #N/A | K11: =VLOOKUP(B11,CREDITO_FINANCEIRO!A:L,12,FALSE) -> #N/A | L11: =MAX(I11:K11) -> #N/A | M11: =IF(((L11)=0),"NÃO, POSSUI VALOR","SIM, POSSUI VALOR") -> #N/A | N11: =VLOOKUP(Tabela4[[#This Row],[Proposta de Referência]],SIMP_CF!A:K,9,FALSE) -> #N/A | O11: =VLOOKUP(Tabela4[[#This Row],[Proposta de Referência]],SIMP_CF!A:K,8,FALSE) -> #N/A | P11: =O11+N11 -> #N/A | Q11: =P11*12 -> #N/A | R11: =IF(P11>=100000,"SIM, POSSUI VALOR ACIMA DE R$100.000,00","NÃO, POSSUI VALOR NECESSÁRIO") -> #N/A | S11: =IF(L11>10000000,"Faixa I - 30%",IF(L11>=5000000,"Faixa II - 40%","Faixa III - 50%")) -> #N/A | T11: =IF(L11>10000000,L11*0.3,IF(L11>=5000000,L11*0.4,L11*0.5)) -> #N/A | U11: =T11-P11 -> #N/A | V11: =IF(OR(U11>=T11,U11<0,T11=0),"NÃO, ATENDEU O CRITÉRIO","SIM, ATENDEU O CRITÉRIO") -> #N/A | W11: =LEFT(D11,8) | X11: =IFERROR(VLOOKUP(W11,HOSPITAIS_COM_DIVIDAS!A:E,5,FALSE),"")
A12: =IFERROR((Tabela4[[#This Row],[Status da Proposta]]),"") | B12: =IFERROR((CREDITO_FINANCEIRO!A12),"") -> 0 | C12: =IFERROR((VLOOKUP(B12,CREDITO_FINANCEIRO!A:B,2,FALSE)),"") | D12: =IFERROR((VLOOKUP(B12,CREDITO_FINANCEIRO!A:E,5,FALSE)),"") | E12: =IFERROR((VLOOKUP(B12,CREDITO_FINANCEIRO!A:C,3,FALSE)),"") | F12: =IFERROR((VLOOKUP(B12,CREDITO_FINANCEIRO!A:G,4,FALSE)),"") | G12: =VLOOKUP(B12,CREDITO_FINANCEIRO!A:G,6,FALSE) -> #N/A | H12: =VLOOKUP(B12,CREDITO_FINANCEIRO!A:G,7,FALSE) -> #N/A | I12: =VLOOKUP(B12,CREDITO_FINANCEIRO!A:K,10,FALSE) -> #N/A | J12: =VLOOKUP(B12,CREDITO_FINANCEIRO!A:K,11,FALSE) -> #N/A | K12: =VLOOKUP(B12,CREDITO_FINANCEIRO!A:L,12,FALSE) -> #N/A | L12: =MAX(I12:K12) -> #N/A | M12: =IF(((L12)=0),"NÃO, POSSUI VALOR","SIM, POSSUI VALOR") -> #N/A | N12: =VLOOKUP(Tabela4[[#This Row],[Proposta de Referência]],SIMP_CF!A:K,9,FALSE) -> #N/A | O12: =VLOOKUP(Tabela4[[#This Row],[Proposta de Referência]],SIMP_CF!A:K,8,FALSE) -> #N/A | P12: =O12+N12 -> #N/A | Q12: =P12*12 -> #N/A | R12: =IF(P12>=100000,"SIM, POSSUI VALOR ACIMA DE R$100.000,00","NÃO, POSSUI VALOR NECESSÁRIO") -> #N/A | S12: =IF(L12>10000000,"Faixa I - 30%",IF(L12>=5000000,"Faixa II - 40%","Faixa III - 50%")) -> #N/A | T12: =IF(L12>10000000,L12*0.3,IF(L12>=5000000,L12*0.4,L12*0.5)) -> #N/A | U12: =T12-P12 -> #N/A | V12: =IF(OR(U12>=T12,U12<0,T12=0),"NÃO, ATENDEU O CRITÉRIO","SIM, ATENDEU O CRITÉRIO") -> #N/A | W12: =LEFT(D12,8) | X12: =IFERROR(VLOOKUP(W12,HOSPITAIS_COM_DIVIDAS!A:E,5,FALSE),"")
A13: =IFERROR((Tabela4[[#This Row],[Status da Proposta]]),"") | B13: =IFERROR((CREDITO_FINANCEIRO!A13),"") -> 0 | C13: =IFERROR((VLOOKUP(B13,CREDITO_FINANCEIRO!A:B,2,FALSE)),"") | D13: =IFERROR((VLOOKUP(B13,CREDITO_FINANCEIRO!A:E,5,FALSE)),"") | E13: =IFERROR((VLOOKUP(B13,CREDITO_FINANCEIRO!A:C,3,FALSE)),"") | F13: =IFERROR((VLOOKUP(B13,CREDITO_FINANCEIRO!A:G,4,FALSE)),"") | G13: =VLOOKUP(B13,CREDITO_FINANCEIRO!A:G,6,FALSE) -> #N/A | H13: =VLOOKUP(B13,CREDITO_FINANCEIRO!A:G,7,FALSE) -> #N/A | I13: =VLOOKUP(B13,CREDITO_FINANCEIRO!A:K,10,FALSE) -> #N/A | J13: =VLOOKUP(B13,CREDITO_FINANCEIRO!A:K,11,FALSE) -> #N/A | K13: =VLOOKUP(B13,CREDITO_FINANCEIRO!A:L,12,FALSE) -> #N/A | L13: =MAX(I13:K13) -> #N/A | M13: =IF(((L13)=0),"NÃO, POSSUI VALOR","SIM, POSSUI VALOR") -> #N/A | N13: =VLOOKUP(Tabela4[[#This Row],[Proposta de Referência]],SIMP_CF!A:K,9,FALSE) -> #N/A | O13: =VLOOKUP(Tabela4[[#This Row],[Proposta de Referência]],SIMP_CF!A:K,8,FALSE) -> #N/A | P13: =O13+N13 -> #N/A | Q13: =P13*12 -> #N/A | R13: =IF(P13>=100000,"SIM, POSSUI VALOR ACIMA DE R$100.000,00","NÃO, POSSUI VALOR NECESSÁRIO") -> #N/A | S13: =IF(L13>10000000,"Faixa I - 30%",IF(L13>=5000000,"Faixa II - 40%","Faixa III - 50%")) -> #N/A | T13: =IF(L13>10000000,L13*0.3,IF(L13>=5000000,L13*0.4,L13*0.5)) -> #N/A | U13: =T13-P13 -> #N/A | V13: =IF(OR(U13>=T13,U13<0,T13=0),"NÃO, ATENDEU O CRITÉRIO","SIM, ATENDEU O CRITÉRIO") -> #N/A | W13: =LEFT(D13,8) | X13: =IFERROR(VLOOKUP(W13,HOSPITAIS_COM_DIVIDAS!A:E,5,FALSE),"")
A14: =IFERROR((Tabela4[[#This Row],[Status da Proposta]]),"") | B14: =IFERROR((CREDITO_FINANCEIRO!A14),"") -> 0 | C14: =IFERROR((VLOOKUP(B14,CREDITO_FINANCEIRO!A:B,2,FALSE)),"") | D14: =IFERROR((VLOOKUP(B14,CREDITO_FINANCEIRO!A:E,5,FALSE)),"") | E14: =IFERROR((VLOOKUP(B14,CREDITO_FINANCEIRO!A:C,3,FALSE)),"") | F14: =IFERROR((VLOOKUP(B14,CREDITO_FINANCEIRO!A:G,4,FALSE)),"") | G14: =VLOOKUP(B14,CREDITO_FINANCEIRO!A:G,6,FALSE) -> #N/A | H14: =VLOOKUP(B14,CREDITO_FINANCEIRO!A:G,7,FALSE) -> #N/A | I14: =VLOOKUP(B14,CREDITO_FINANCEIRO!A:K,10,FALSE) -> #N/A | J14: =VLOOKUP(B14,CREDITO_FINANCEIRO!A:K,11,FALSE) -> #N/A | K14: =VLOOKUP(B14,CREDITO_FINANCEIRO!A:L,12,FALSE) -> #N/A | L14: =MAX(I14:K14) -> #N/A | M14: =IF(((L14)=0),"NÃO, POSSUI VALOR","SIM, POSSUI VALOR") -> #N/A | N14: =VLOOKUP(Tabela4[[#This Row],[Proposta de Referência]],SIMP_CF!A:K,9,FALSE) -> #N/A | O14: =VLOOKUP(Tabela4[[#This Row],[Proposta de Referência]],SIMP_CF!A:K,8,FALSE) -> #N/A | P14: =O14+N14 -> #N/A | Q14: =P14*12 -> #N/A | R14: =IF(P14>=100000,"SIM, POSSUI VALOR ACIMA DE R$100.000,00","NÃO, POSSUI VALOR NECESSÁRIO") -> #N/A | S14: =IF(L14>10000000,"Faixa I - 30%",IF(L14>=5000000,"Faixa II - 40%","Faixa III - 50%")) -> #N/A | T14: =IF(L14>10000000,L14*0.3,IF(L14>=5000000,L14*0.4,L14*0.5)) -> #N/A | U14: =T14-P14 -> #N/A | V14: =IF(OR(U14>=T14,U14<0,T14=0),"NÃO, ATENDEU O CRITÉRIO","SIM, ATENDEU O CRITÉRIO") -> #N/A | W14: =LEFT(D14,8) | X14: =IFERROR(VLOOKUP(W14,HOSPITAIS_COM_DIVIDAS!A:E,5,FALSE),"")
... A1748: =IFERROR((Tabela4[[#This Row],[Status da Proposta]]),"") | B1748: =IFERROR((CREDITO_FINANCEIRO!A1748),"") -> 0 | C1748: =IFERROR((VLOOKUP(B1748,CREDITO_FINANCEIRO!A:B,2,FALSE)),"") | D1748: =IFERROR((VLOOKUP(B1748,CREDITO_FINANCEIRO!A:E,5,FALSE)),"") | E1748: =IFERROR((VLOOKUP(B1748,CREDITO_FINANCEIRO!A:C,3,FALSE)),"") | F1748: =IFERROR((VLOOKUP(B1748,CREDITO_FINANCEIRO!A:G,4,FALSE)),"") | G1748: =VLOOKUP(B1748,CREDITO_FINANCEIRO!A:G,6,FALSE) -> #N/A | H1748: =VLOOKUP(B1748,CREDITO_FINANCEIRO!A:G,7,FALSE) -> #N/A | I1748: =VLOOKUP(B1748,CREDITO_FINANCEIRO!A:K,10,FALSE) -> #N/A | J1748: =VLOOKUP(B1748,CREDITO_FINANCEIRO!A:K,11,FALSE) -> #N/A | K1748: =VLOOKUP(B1748,CREDITO_FINANCEIRO!A:L,12,FALSE) -> #N/A | L1748: =MAX(I1748:K1748) -> #N/A | M1748: =IF(((L1748)=0),"NÃO, POSSUI VALOR","SIM, POSSUI VALOR") -> #N/A | N1748: =VLOOKUP(Tabela4[[#This Row],[Proposta de Referência]],SIMP_CF!A:K,9,FALSE) -> #N/A | O1748: =VLOOKUP(Tabela4[[#This Row],[Proposta de Referência]],SIMP_CF!A:K,8,FALSE) -> #N/A | P1748: =O1748+N1748 -> #N/A | Q1748: =P1748*12 -> #N/A | R1748: =IF(P1748>=100000,"SIM, POSSUI VALOR ACIMA DE R$100.000,00","NÃO, POSSUI VALOR NECESSÁRIO") -> #N/A | S1748: =IF(L1748>10000000,"Faixa I - 30%",IF(L1748>=5000000,"Faixa II - 40%","Faixa III - 50%")) -> #N/A | T1748: =IF(L1748>10000000,L1748*0.3,IF(L1748>=5000000,L1748*0.4,L1748*0.5)) -> #N/A | U1748: =T1748-P1748 -> #N/A | V1748: =IF(OR(U1748>=T1748,U1748<0,T1748=0),"NÃO, ATENDEU O CRITÉRIO","SIM, ATENDEU O CRITÉRIO") -> #N/A | W1748: =LEFT(D1748,8) | X1748: =IFERROR(VLOOKUP(W1748,HOSPITAIS_COM_DIVIDAS!A:E,5,FALSE),"")

Sheet SIMP_CF
A1: VISÃO SIMPLIFICADO - CRÉDITO FINANCEIRO
A2: Proposta de Referência | B2: Status da Proposta | C2: CNES | D2: ENTIDADE | E2: CNPJ | F2: UF | G2: MUNICIPIO | H2: VL_TOTAL_COMP_CIRUGICO | I2: VL_TOTAL_OCI | J2: VALOR_TOTAL_MES_COMP+OCI | K2: VALOR_TOTAL_ANUAL_COMP+OCI
H3: 1 | I3: 1 | J3: 1 | K3: 1

Sheet M_OFERTA_CF_CC
A1: MATRIZ DE OFERTA - CRÉDITO FINANCEIRO - CIRURGIAS
A2: Proposta de Referência | B2: Status da Proposta | C2: UF | D2: Município | E2: CNES | F2: ENTIDADE | G2: CO_PROCEDIMENTO_SIGTAP | H2: NOME DO GRUPO | I2: NO_GRUPO | J2: NO_PROCEDIMENTO | K2: % COMPLEMENTACAO_MAXIMA | L2: VL_TABELA_SUS | M2: VL_TOTAL_COMPLEMENTACAO_MAXIMA | N2: VL_ACRESCIMO_BRASIL | O2: QT_ATENDIMENTO_MES | P2: VALOR TOTAL MÊS
M3: 1 | N3: 1 | O3: 1 | P3: 1

Sheet M_OFERTA_CF_OCI
A1: MATRIZ DE OFERTA - CRÉDITO FINANCEIRO - OCI
A2: Proposta de Referência | B2: Status da Proposta | C2: UF | D2: Município | E2: CNES | F2: ENTIDADE | G2: NU_PROCEDIMENTO | H2: NOME DO GRUPO | I2: NOME DO PROCEDIMENTO | J2: AGRUPAMENTO | K2: QTD ATENDIMENTO MES | L2: VALOR DO PROCEDIMENTO | M2: VALOR TOTAL MÊS
K3: 1 | L3: 1 | M3: 1

Sheet MODALIDADE_1
A1: Proposta de Referência | B1: Status da Proposta | C1: CNES | D1: Entidade | E1: CNPJ | F1: UF | G1: Município | H1: Dt. Cadastro | I1: Dt. Atualização

Sheet VISÃO_GERAL_M1
A1: TOTAL | B1: =(SUMPRODUCT(1/COUNTIF(B3:B8106,B3:B8106&"")))-1 -> 1 | G1: ATUALIZAÇÃO 29/09/2025 - 15:30 | H1: =(SUMPRODUCT(1/COUNTIF(H3:H8106,H3:H8106&"")))-1 -> 1 | I1: =(SUMPRODUCT(1/COUNTIF(I3:I8106,I3:I8106&"")))-1 -> 1 | J1: =SUBTOTAL(109,J3:J1048576) -> #N/A | K1: =SUBTOTAL(109,K3:K1048576) -> #N/A | L1: =SUBTOTAL(109,L3:L1048576) -> #N/A | M1: =SUBTOTAL(109,M3:M1048576) -> #N/A | P1: =SUBTOTAL(109,P3:P1048576) -> 0
A2: Status da Proposta - DEEQAE | B2: Proposta de Referência | C2: Status da Proposta | D2: cancelamento CCPP | E2: CNPJ | F2: CNES | G2: Entidade | H2: UF | I2: Município | J2: VL_OFERTA_OCI MÊS | K2: VL_OFERTA_COMP_CIRUR MÊS | L2: VALOR SOMADO DAS OFERTAS MÊS | M2: VALOR SOMADO DAS OFERTAS POR ANO | N2: 1ª análise - verificar se a matriz de oferta está acima de 100mil - art.7º; | O2: CNPJ CURTO | P2: DIVIDA HOSPITAL POR CNPJ
A3: =Tabela410[[#This Row],[Status da Proposta]] -> #N/A | B3: =MODALIDADE_1!A3 -> 0 | C3: =VLOOKUP(B3,MODALIDADE_1!A:B,2,FALSE) -> #N/A | E3: =VLOOKUP(B3,MODALIDADE_1!A:E,5,FALSE) -> #N/A | F3: =VLOOKUP(B3,MODALIDADE_1!A:C,3,FALSE) -> #N/A | G3: =VLOOKUP(B3,MODALIDADE_1!A:G,4,FALSE) -> #N/A | H3: =VLOOKUP(B3,MODALIDADE_1!A:G,6,FALSE) -> #N/A | I3: =VLOOKUP(B3,MODALIDADE_1!A:G,7,FALSE) -> #N/A | J3: =VLOOKUP(Tabela410[[#This Row],[Proposta de Referência]],SIMP_M1!A:K,9,FALSE) -> #N/A | K3: =VLOOKUP(Tabela410[[#This Row],[Proposta de Referência]],SIMP_M1!A:K,8,FALSE) -> #N/A | L3: =K3+J3 -> #N/A | M3: =L3*12 -> #N/A | N3: =IF(L3>100000,"SIM, POSSUI VALOR ACIMA DE R$100.000,00","NÃO, POSSUI VALOR NECESSÁRIO") -> #N/A | O3: =LEFT(E3,8) -> #N/A | P3: =IFERROR(VLOOKUP(O3,HOSPITAIS_COM_DIVIDAS!A:E,5,FALSE),"")
A4: =Tabela410[[#This Row],[Status da Proposta]] -> #N/A | B4: =MODALIDADE_1!A4 -> 0 | C4: =VLOOKUP(B4,MODALIDADE_1!A:B,2,FALSE) -> #N/A | E4: =VLOOKUP(B4,MODALIDADE_1!A:E,5,FALSE) -> #N/A | F4: =VLOOKUP(B4,MODALIDADE_1!A:C,3,FALSE) -> #N/A | G4: =VLOOKUP(B4,MODALIDADE_1!A:G,4,FALSE) -> #N/A | H4: =VLOOKUP(B4,MODALIDADE_1!A:G,6,FALSE) -> #N/A | I4: =VLOOKUP(B4,MODALIDADE_1!A:G,7,FALSE) -> #N/A | J4: =VLOOKUP(Tabela410[[#This Row],[Proposta de Referência]],SIMP_M1!A:K,9,FALSE) -> #N/A | K4: =VLOOKUP(Tabela410[[#This Row],[Proposta de Referência]],SIMP_M1!A:K,8,FALSE) -> #N/A | L4: =K4+J4 -> #N/A | M4: =L4*12 -> #N/A | N4: =IF(L4>100000,"SIM, POSSUI VALOR ACIMA DE R$100.000,00","NÃO, POSSUI VALOR NECESSÁRIO") -> #N/A | O4: =LEFT(E4,8) -> #N/A | P4: =IFERROR(VLOOKUP(O4,HOSPITAIS_COM_DIVIDAS!A:E,5,FALSE),"")
A5: =Tabela410[[#This Row],[Status da Proposta]] -> #N/A | B5: =MODALIDADE_1!A5 -> 0 | C5: =VLOOKUP(B5,MODALIDADE_1!A:B,2,FALSE) -> #N/A | E5: =VLOOKUP(B5,MODALIDADE_1!A:E,5,FALSE) -> #N/A | F5: =VLOOKUP(B5,MODALIDADE_1!A:C,3,FALSE) -> #N/A | G5: =VLOOKUP(B5,MODALIDADE_1!A:G,4,FALSE) -> #N/A | H5: =VLOOKUP(B5,MODALIDADE_1!A:G,6,FALSE) -> #N/A | I5: =VLOOKUP(B5,MODALIDADE_1!A:G,7,FALSE) -> #N/A | J5: =VLOOKUP(Tabela410[[#This Row],[Proposta de Referência]],SIMP_M1!A:K,9,FALSE) -> #N/A | K5: =VLOOKUP(Tabela410[[#This Row],[Proposta de Referência]],SIMP_M1!A:K,8,FALSE) -> #N/A | L5: =K5+J5 -> #N/A | M5: =L5*12 -> #N/A | N5: =IF(L5>100000,"SIM, POSSUI VALOR ACIMA DE R$100.000,00","NÃO, POSSUI VALOR NECESSÁRIO") -> #N/A | O5: =LEFT(E5,8) -> #N/A | P5: =IFERROR(VLOOKUP(O5,HOSPITAIS_COM_DIVIDAS!A:E,5,FALSE),"")
A6: =Tabela410[[#This Row],[Status da Proposta]] -> #N/A | B6: =MODALIDADE_1!A6 -> 0 | C6: =VLOOKUP(B6,MODALIDADE_1!A:B,2,FALSE) -> #N/A | E6: =VLOOKUP(B6,MODALIDADE_1!A:E,5,FALSE) -> #N/A | F6: =VLOOKUP(B6,MODALIDADE_1!A:C,3,FALSE) -> #N/A | G6: =VLOOKUP(B6,MODALIDADE_1!A:G,4,FALSE) -> #N/A | H6: =VLOOKUP(B6,MODALIDADE_1!A:G,6,FALSE) -> #N/A | I6: =VLOOKUP(B6,MODALIDADE_1!A:G,7,FALSE) -> #N/A | J6: =VLOOKUP(Tabela410[[#This Row],[Proposta de Referência]],SIMP_M1!A:K,9,FALSE) -> #N/A | K6: =VLOOKUP(Tabela410[[#This Row],[Proposta de Referência]],SIMP_M1!A:K,8,FALSE) -> #N/A | L6: =K6+J6 -> #N/A | M6: =L6*12 -> #N/A | N6: =IF(L6>100000,"SIM, POSSUI VALOR ACIMA DE R$100.000,00","NÃO, POSSUI VALOR NECESSÁRIO") -> #N/A | O6: =LEFT(E6,8) -> #N/A | P6: =IFERROR(VLOOKUP(O6,HOSPITAIS_COM_DIVIDAS!A:E,5,FALSE),"")
A7: =Tabela410[[#This Row],[Status da Proposta]] -> #N/A | B7: =MODALIDADE_1!A7 -> 0 | C7: =VLOOKUP(B7,MODALIDADE_1!A:B,2,FALSE) -> #N/A | E7: =VLOOKUP(B7,MODALIDADE_1!A:E,5,FALSE) -> #N/A | F7: =VLOOKUP(B7,MODALIDADE_1!A:C,3,FALSE) -> #N/A | G7: =VLOOKUP(B7,MODALIDADE_1!A:G,4,FALSE) -> #N/A | H7: =VLOOKUP(B7,MODALIDADE_1!A:G,6,FALSE) -> #N/A | I7: =VLOOKUP(B7,MODALIDADE_1!A:G,7,FALSE) -> #N/A | J7: =VLOOKUP(Tabela410[[#This Row],[Proposta de Referência]],SIMP_M1!A:K,9,FALSE) -> #N/A | K7: =VLOOKUP(Tabela410[[#This Row],[Proposta de Referência]],SIMP_M1!A:K,8,FALSE) -> #N/A | L7: =K7+J7 -> #N/A | M7: =L7*12 -> #N/A | N7: =IF(L7>100000,"SIM, POSSUI VALOR ACIMA DE R$100.000,00","NÃO, POSSUI VALOR NECESSÁRIO") -> #N/A | O7: =LEFT(E7,8) -> #N/A | P7: =IFERROR(VLOOKUP(O7,HOSPITAIS_COM_DIVIDAS!A:E,5,FALSE),"")
A8: =Tabela410[[#This Row],[Status da Proposta]] -> #N/A | B8: =MODALIDADE_1!A8 -> 0 | C8: =VLOOKUP(B8,MODALIDADE_1!A:B,2,FALSE) -> #N/A | E8: =VLOOKUP(B8,MODALIDADE_1!A:E,5,FALSE) -> #N/A | F8: =VLOOKUP(B8,MODALIDADE_1!A:C,3,FALSE) -> #N/A | G8: =VLOOKUP(B8,MODALIDADE_1!A:G,4,FALSE) -> #N/A | H8: =VLOOKUP(B8,MODALIDADE_1!A:G,6,FALSE) -> #N/A | I8: =VLOOKUP(B8,MODALIDADE_1!A:G,7,FALSE) -> #N/A | J8: =VLOOKUP(Tabela410[[#This Row],[Proposta de Referência]],SIMP_M1!A:K,9,FALSE) -> #N/A | K8: =VLOOKUP(Tabela410[[#This Row],[Proposta de Referência]],SIMP_M1!A:K,8,FALSE) -> #N/A | L8: =K8+J8 -> #N/A | M8: =L8*12 -> #N/A | N8: =IF(L8>100000,"SIM, POSSUI VALOR ACIMA DE R$100.000,00","NÃO, POSSUI VALOR NECESSÁRIO") -> #N/A | O8: =LEFT(E8,8) -> #N/A | P8: =IFERROR(VLOOKUP(O8,HOSPITAIS_COM_DIVIDAS!A:E,5,FALSE),"")
A9: =Tabela410[[#This Row],[Status da Proposta]] -> #N/A | B9: =MODALIDADE_1!A9 -> 0 | C9: =VLOOKUP(B9,MODALIDADE_1!A:B,2,FALSE) -> #N/A | E9: =VLOOKUP(B9,MODALIDADE_1!A:E,5,FALSE) -> #N/A | F9: =VLOOKUP(B9,MODALIDADE_1!A:C,3,FALSE) -> #N/A | G9: =VLOOKUP(B9,MODALIDADE_1!A:G,4,FALSE) -> #N/A | H9: =VLOOKUP(B9,MODALIDADE_1!A:G,6,FALSE) -> #N/A | I9: =VLOOKUP(B9,MODALIDADE_1!A:G,7,FALSE) -> #N/A | J9: =VLOOKUP(Tabela410[[#This Row],[Proposta de Referência]],SIMP_M1!A:K,9,FALSE) -> #N/A | K9: =VLOOKUP(Tabela410[[#This Row],[Proposta de Referência]],SIMP_M1!A:K,8,FALSE) -> #N/A | L9: =K9+J9 -> #N/A | M9: =L9*12 -> #N/A | N9: =IF(L9>100000,"SIM, POSSUI VALOR ACIMA DE R$100.000,00","NÃO, POSSUI VALOR NECESSÁRIO") -> #N/A | O9: =LEFT(E9,8) -> #N/A | P9: =IFERROR(VLOOKUP(O9,HOSPITAIS_COM_DIVIDAS!A:E,5,FALSE),"")
A10: =Tabela410[[#This Row],[Status da Proposta]] -> #N/A | B10: =MODALIDADE_1!A10 -> 0 | C10: =VLOOKUP(B10,MODALIDADE_1!A:B,2,FALSE) -> #N/A | E10: =VLOOKUP(B10,MODALIDADE_1!A:E,5,FALSE) -> #N/A | F10: =VLOOKUP(B10,MODALIDADE_1!A:C,3,FALSE) -> #N/A | G10: =VLOOKUP(B10,MODALIDADE_1!A:G,4,FALSE) -> #N/A | H10: =VLOOKUP(B10,MODALIDADE_1!A:G,6,FALSE) -> #N/A | I10: =VLOOKUP(B10,MODALIDADE_1!A:G,7,FALSE) -> #N/A | J10: =VLOOKUP(Tabela410[[#This Row],[Proposta de Referência]],SIMP_M1!A:K,9,FALSE) -> #N/A | K10: =VLOOKUP(Tabela410[[#This Row],[Proposta de Referência]],SIMP_M1!A:K,8,FALSE) -> #N/A | L10: =K10+J10 -> #N/A | M10: =L10*12 -> #N/A | N10: =IF(L10>100000,"SIM, POSSUI VALOR ACIMA DE R$100.000,00","NÃO, POSSUI VALOR NECESSÁRIO") -> #N/A | O10: =LEFT(E10,8) -> #N/A | P10: =IFERROR(VLOOKUP(O10,HOSPITAIS_COM_DIVIDAS!A:E,5,FALSE),"")
A11: =Tabela410[[#This Row],[Status da Proposta]] -> #N/A | B11: =MODALIDADE_1!A11 -> 0 | C11: =VLOOKUP(B11,MODALIDADE_1!A:B,2,FALSE) -> #N/A | E11: =VLOOKUP(B11,MODALIDADE_1!A:E,5,FALSE) -> #N/A | F11: =VLOOKUP(B11,MODALIDADE_1!A:C,3,FALSE) -> #N/A | G11: =VLOOKUP(B11,MODALIDADE_1!A:G,4,FALSE) -> #N/A | H11: =VLOOKUP(B11,MODALIDADE_1!A:G,6,FALSE) -> #N/A | I11: =VLOOKUP(B11,MODALIDADE_1!A:G,7,FALSE) -> #N/A | J11: =VLOOKUP(Tabela410[[#This Row],[Proposta de Referência]],SIMP_M1!A:K,9,FALSE) -> #N/A | K11: =VLOOKUP(Tabela410[[#This Row],[Proposta de Referência]],SIMP_M1!A:K,8,FALSE) -> #N/A | L11: =K11+J11 -> #N/A | M11: =L11*12 -> #N/A | N11: =IF(L11>100000,"SIM, POSSUI VALOR ACIMA DE R$100.000,00","NÃO, POSSUI VALOR NECESSÁRIO") -> #N/A | O11: =LEFT(E11,8) -> #N/A | P11: =IFERROR(VLOOKUP(O11,HOSPITAIS_COM_DIVIDAS!A:E,5,FALSE),"")
A12: =Tabela410[[#This Row],[Status da Proposta]] -> #N/A | B12: =MODALIDADE_1!A12 -> 0 | C12: =VLOOKUP(B12,MODALIDADE_1!A:B,2,FALSE) -> #N/A | E12: =VLOOKUP(B12,MODALIDADE_1!A:E,5,FALSE) -> #N/A | F12: =VLOOKUP(B12,MODALIDADE_1!A:C,3,FALSE) -> #N/A | G12: =VLOOKUP(B12,MODALIDADE_1!A:G,4,FALSE) -> #N/A | H12: =VLOOKUP(B12,MODALIDADE_1!A:G,6,FALSE) -> #N/A | I12: =VLOOKUP(B12,MODALIDADE_1!A:G,7,FALSE) -> #N/A | J12: =VLOOKUP(Tabela410[[#This Row],[Proposta de Referência]],SIMP_M1!A:K,9,FALSE) -> #N/A | K12: =VLOOKUP(Tabela410[[#This Row],[Proposta de Referência]],SIMP_M1!A:K,8,FALSE) -> #N/A | L12: =K12+J12 -> #N/A | M12: =L12*12 -> #N/A | N12: =IF(L12>100000,"SIM, POSSUI VALOR ACIMA DE R$100.000,00","NÃO, POSSUI VALOR NECESSÁRIO") -> #N/A | O12: =LEFT(E12,8) -> #N/A | P12: =IFERROR(VLOOKUP(O12,HOSPITAIS_COM_DIVIDAS!A:E,5,FALSE),"")
A13: =Tabela410[[#This Row],[Status da Proposta]] -> #N/A | B13: =MODALIDADE_1!A13 -> 0 | C13: =VLOOKUP(B13,MODALIDADE_1!A:B,2,FALSE) -> #N/A | E13: =VLOOKUP(B13,MODALIDADE_1!A:E,5,FALSE) -> #N/A | F13: =VLOOKUP(B13,MODALIDADE_1!A:C,3,FALSE) -> #N/A | G13: =VLOOKUP(B13,MODALIDADE_1!A:G,4,FALSE) -> #N/A | H13: =VLOOKUP(B13,MODALIDADE_1!A:G,6,FALSE) -> #N/A | I13: =VLOOKUP(B13,MODALIDADE_1!A:G,7,FALSE) -> #N/A | J13: =VLOOKUP(Tabela410[[#This Row],[Proposta de Referência]],SIMP_M1!A:K,9,FALSE) -> #N/A | K13: =VLOOKUP(Tabela410[[#This Row],[Proposta de Referência]],SIMP_M1!A:K,8,FALSE) -> #N/A | L13: =K13+J13 -> #N/A | M13: =L13*12 -> #N/A | N13: =IF(L13>100000,"SIM, POSSUI VALOR ACIMA DE R$100.000,00","NÃO, POSSUI VALOR NECESSÁRIO") -> #N/A | O13: =LEFT(E13,8) -> #N/A | P13: =IFERROR(VLOOKUP(O13,HOSPITAIS_COM_DIVIDAS!A:E,5,FALSE),"")
A14: =Tabela410[[#This Row],[Status da Proposta]] -> #N/A | B14: =MODALIDADE_1!A14 -> 0 | C14: =VLOOKUP(B14,MODALIDADE_1!A:B,2,FALSE) -> #N/A | E14: =VLOOKUP(B14,MODALIDADE_1!A:E,5,FALSE) -> #N/A | F14: =VLOOKUP(B14,MODALIDADE_1!A:C,3,FALSE) -> #N/A | G14: =VLOOKUP(B14,MODALIDADE_1!A:G,4,FALSE) -> #N/A | H14: =VLOOKUP(B14,MODALIDADE_1!A:G,6,FALSE) -> #N/A | I14: =VLOOKUP(B14,MODALIDADE_1!A:G,7,FALSE) -> #N/A | J14: =VLOOKUP(Tabela410[[#This Row],[Proposta de Referência]],SIMP_M1!A:K,9,FALSE) -> #N/A | K14: =VLOOKUP(Tabela410[[#This Row],[Proposta de Referência]],SIMP_M1!A:K,8,FALSE) -> #N/A | L14: =K14+J14 -> #N/A | M14: =L14*12 -> #N/A | N14: =IF(L14>100000,"SIM, POSSUI VALOR ACIMA DE R$100.000,00","NÃO, POSSUI VALOR NECESSÁRIO") -> #N/A | O14: =LEFT(E14,8) -> #N/A | P14: =IFERROR(VLOOKUP(O14,HOSPITAIS_COM_DIVIDAS!A:E,5,FALSE),"")
... A3164: =Tabela410[[#This Row],[Status da Proposta]] -> #VALUE! | B3164: =MODALIDADE_1!A3164 -> 0 | C3164: =VLOOKUP(B3164,MODALIDADE_1!A:B,2,FALSE) -> #N/A | E3164: =VLOOKUP(B3164,MODALIDADE_1!A:E,5,FALSE) -> #N/A | F3164: =VLOOKUP(B3164,MODALIDADE_1!A:C,3,FALSE) -> #N/A | G3164: =VLOOKUP(B3164,MODALIDADE_1!A:G,4,FALSE) -> #N/A | H3164: =VLOOKUP(B3164,MODALIDADE_1!A:G,6,FALSE) -> #N/A | I3164: =VLOOKUP(B3164,MODALIDADE_1!A:G,7,FALSE) -> #N/A | J3164: =VLOOKUP(Tabela410[[#This Row],[Proposta de Referência]],SIMP_M1!A:K,9,FALSE) -> #VALUE! | K3164: =VLOOKUP(Tabela410[[#This Row],[Proposta de Referência]],SIMP_M1!A:K,8,FALSE) -> #VALUE! | L3164: =K3164+J3164 -> #VALUE! | M3164: =L3164*12 -> #VALUE! | N3164: =IF(L3164>100000,"SIM, POSSUI VALOR ACIMA DE R$100.000,00","NÃO, POSSUI VALOR NECESSÁRIO") -> #VALUE! | O3164: =LEFT(E3164,8) -> #N/A | P3164: =IFERROR(VLOOKUP(O3164,HOSPITAIS_COM_DIVIDAS!A:E,5,FALSE),"")

Sheet M_OFERTA_M1_CC
A1: MATRIZ DE OFERTA - MODALIDADE 1 - CIRURGIAS
A2: Proposta de Referência | B2: Status da Proposta | C2: UF | D2: Município | E2: CNES | F2: ENTIDADE | G2: CO_PROCEDIMENTO_SIGTAP | H2: NOME DO GRUPO | I2: NO_GRUPO | J2: NO_PROCEDIMENTO | K2: % COMPLEMENTACAO_MAXIMA | L2: VL_TABELA_SUS | M2: VL_TOTAL_COMPLEMENTACAO_MAXIMA | N2: VL_ACRESCIMO_BRASIL | O2: QT_ATENDIMENTO_MES | P2: VALOR TOTAL MÊS
L3: 1 | M3: 1 | N3: 1 | O3: 1 | P3: 1

Sheet SIMP_M1
A1: VISÃO SIMPLIFICADO - MODALIDADE 1
A2: Proposta de Referência | B2: Status da Proposta | C2: CNES | D2: ENTIDADE | E2: CNPJ | F2: UF | G2: MUNICIPIO | H2: VL_TOTAL_COMP_CIRUGICO | I2: VL_TOTAL_OCI | J2: VALOR_TOTAL_MES_COMP+OCI | K2: VALOR_TOTAL_ANUAL_COMP+OCI
H3: 1 | I3: 1 | J3: 1 | K3: 1

Sheet M_OFERTA_M1_OCI
A1: MATRIZ DE OFERTA - CRÉDITO FINANCEIRO - OCI
A2: Proposta de Referência | B2: Status da Proposta | C2: UF | D2: Município | E2: CNES | F2: ENTIDADE | G2: NU_PROCEDIMENTO | H2: NOME DO GRUPO | I2: NOME DO PROCEDIMENTO | J2: AGRUPAMENTO | K2: QTD ATENDIMENTO MES | L2: VALOR DO PROCEDIMENTO2 | M2: VALOR TOTAL MÊS
K3: 1 | L3: 1 | M3: 1

Sheet CCPP-CANCELAR
A1: SOLICITAÇÃO DE CANCELAMENTO DA PROPOSTA
A2: Proposta de Referência | B2: Status da Proposta | C2: CNES | D2: ENTIDADE | E2: CNPJ | F2: UF | G2: MUNICIPIO | H2: VL_TOTAL_COMP_CIRUGICO | I2: VL_TOTAL_OCI | J2: VALOR_TOTAL_MES_COMP+OCI | K2: VALOR_TOTAL_MES_COMP+OCI2

Sheet HOSPITAIS_COM_DIVIDAS
B1: DAU - Hospitais
B3: Filtro do relatório:
B4: ({Tipo Inscrição} <> Contribuições FGTS, Contribuições LC110 (FGTS), Contribuições FGTS e LC110) E ({CNAE Grupo} = Atividades de atendimento hospitalar) E ({Esfera do Ente Federativo Responsável} = Não se aplica)
A6: CNPJ | B6: CPF/CNPJ do Devedor Detalhado | C6: Nome do Devedor Detalhado | D6: UF do Devedor | E6: Todas Origens - Valor Consolidado da Inscrição | F6: Quantidade de Devedores Agregados
A7: =LEFT(SUBSTITUTE(SUBSTITUTE(SUBSTITUTE(SUBSTITUTE(TRIM(B7),".",""),"/",""),"-","")," ",""), 8) -> 00000618 | B7: 00.000.618/0001-51 | C7: HOSPITAL DA REABILITACAO DO ABC LTDA | D7: SAO PAULO | E7: 333869.05 | F7: 1
A8: =LEFT(SUBSTITUTE(SUBSTITUTE(SUBSTITUTE(SUBSTITUTE(TRIM(B8),".",""),"/",""),"-","")," ",""), 8) -> 00020324 | B8: 00.020.324/0001-91 | C8: MEG LESTE HOSPITALAR LTDA | D8: SAO PAULO | E8: 16757537 | F8: 1
A9: =LEFT(SUBSTITUTE(SUBSTITUTE(SUBSTITUTE(SUBSTITUTE(TRIM(B9),".",""),"/",""),"-","")," ",""), 8) -> 00048009 | B9: 00.048.009/0001-72 | C9: ANTONIO CARLOS PEDRO | D9: GOIAS | E9: 289018.61 | F9: 1
A10: =LEFT(SUBSTITUTE(SUBSTITUTE(SUBSTITUTE(SUBSTITUTE(TRIM(B10),".",""),"/",""),"-","")," ",""), 8) -> 00057423 | B10: 00.057.423/0001-48 | C10: SERMECOL SERVICOS MEDICO COLINENSE LTDA | D10: MARANHAO | E10: 16023.86 | F10: 1
A11: =LEFT(SUBSTITUTE(SUBSTITUTE(SUBSTITUTE(SUBSTITUTE(TRIM(B11),".",""),"/",""),"-","")," ",""), 8) -> 00058224 | B11: 00.058.224/0001-54 | C11: HOSPITAL DIA-VIDA E LIBERDADE LTDA | D11: MARANHAO | E11: 49252.96 | F11: 1
A12: =LEFT(SUBSTITUTE(SUBSTITUTE(SUBSTITUTE(SUBSTITUTE(TRIM(B12),".",""),"/",""),"-","")," ",""), 8) -> 00060485 | B12: 00.060.485/0001-09 | C12: PRO MATRE MATERNIDADE LTDA | D12: MATO GROSSO | E12: 83053.62 | F12: 1
A13: =LEFT(SUBSTITUTE(SUBSTITUTE(SUBSTITUTE(SUBSTITUTE(TRIM(B13),".",""),"/",""),"-","")," ",""), 8) -> 00060931 | B13: 00.060.931/0001-85 | C13: SEPESC-SERVICO DE PEDIATRIA DO SANTA CRUZ SC LTDA | D13: MATO GROSSO | E13: 545080.56 | F13: 1
A14: =LEFT(SUBSTITUTE(SUBSTITUTE(SUBSTITUTE(SUBSTITUTE(TRIM(B14),".",""),"/",""),"-","")," ",""), 8) -> 00062519 | B14: 00.062.519/0001-02 | C14: UNIDADE DE CARDIOLOGIA INVASIVA S/C LTDA | D14: PERNAMBUCO | E14: 275309.97 | F14: 1
A15: =LEFT(SUBSTITUTE(SUBSTITUTE(SUBSTITUTE(SUBSTITUTE(TRIM(B15),".",""),"/",""),"-","")," ",""), 8) -> 00063253 | B15: 00.063.253/0001-04 | C15: CLIDIMED SERVICOS MEDICOS LTDA | D15: MATO GROSSO | E15: 348248.33 | F15: 1
A16: =LEFT(SUBSTITUTE(SUBSTITUTE(SUBSTITUTE(SUBSTITUTE(TRIM(B16),".",""),"/",""),"-","")," ",""), 8) -> 00070400 | B16: 00.070.400/0001-73 | C16: HOSPITAL NOSSA SENHORA DA PENHA LIMITADA | D16: SANTA CATARINA | E16: 395876.45 | F16: 1
A17: =LEFT(SUBSTITUTE(SUBSTITUTE(SUBSTITUTE(SUBSTITUTE(TRIM(B17),".",""),"/",""),"-","")," ",""), 8) -> 00071178 | B17: 00.071.178/0001-23 | C17: CENTRO DE OLHOS DE SAO LUIS LTDA | D17: MARANHAO | E17: 5923504 | F17: 1
A18: =LEFT(SUBSTITUTE(SUBSTITUTE(SUBSTITUTE(SUBSTITUTE(TRIM(B18),".",""),"/",""),"-","")," ",""), 8) -> 00098888 | B18: 00.098.888/0001-47 | C18: MATERNIDADE MATER DEI S/C LIMITADA | D18: PARANA | E18: 180294.66 | F18: 1
... A3570: =LEFT(SUBSTITUTE(SUBSTITUTE(SUBSTITUTE(SUBSTITUTE(TRIM(B3570),".",""),"/",""),"-","")," ",""), 8) -> 92781046 | B3570: 92.781.046/0001-03 | C3570: SERVICO DE TRANSFUSAO DE SANGUE REUNIDOS SA | D3570: RIO GRANDE DO SUL | E3570: 1410237.6 | F3570: 1
A3571: =LEFT(SUBSTITUTE(SUBSTITUTE(SUBSTITUTE(SUBSTITUTE(TRIM(B3571),".",""),"/",""),"-","")," ",""), 8) -> 92815000 | B3571: 92.815.000/0001-68 | C3571: IRMANDADE DA SANTA CASA DE MISERICORDIA DE PORTO ALEGRE | D3571: RIO GRANDE DO SUL | E3571: 469974.82 | F3571: 1 | H3571: =E3571*12 -> 5639697.8
A3572: =LEFT(SUBSTITUTE(SUBSTITUTE(SUBSTITUTE(SUBSTITUTE(TRIM(B3572),".",""),"/",""),"-","")," ",""), 8) -> 92820604 | B3572: 92.820.604/0001-00 | C3572: HOSPITAL VILA NOVA LTDA | D3572: RIO GRANDE DO SUL | E3572: 1.8753286e+08 | F3572: 1
A3573: =LEFT(SUBSTITUTE(SUBSTITUTE(SUBSTITUTE(SUBSTITUTE(TRIM(B3573),".",""),"/",""),"-","")," ",""), 8) -> 92831163 | B3573: 92.831.163/0001-34 | C3573: ASSOCIACAO DOS FUNCIONARIOS MUNICIPAIS DE PORTO ALEGRE | D3573: RIO GRANDE DO SUL | E3573: 1.0963503e+08 | F3573: 1
A3574: =LEFT(SUBSTITUTE(SUBSTITUTE(SUBSTITUTE(SUBSTITUTE(TRIM(B3574),".",""),"/",""),"-","")," ",""), 8) -> 92831163 | B3574: 92.831.163/0002-15 | C3574: ASSOCIACAO DOS FUNCIONARIOS MUNICIPAIS DE PORTO ALEGRE | D3574: RIO GRANDE DO SUL | E3574: 5880026.4 | F3574: 1
A3575: =LEFT(SUBSTITUTE(SUBSTITUTE(SUBSTITUTE(SUBSTITUTE(TRIM(B3575),".",""),"/",""),"-","")," ",""), 8) -> 92898550 | B3575: 92.898.550/0001-98 | C3575: FUNDACAO UNIVERSITARIA DE CARDIOLOGIA EM RECUPERACAO JUDICIAL | D3575: RIO GRANDE DO SUL | E3575: 88447492 | F3575: 1
A3576: =LEFT(SUBSTITUTE(SUBSTITUTE(SUBSTITUTE(SUBSTITUTE(TRIM(B3576),".",""),"/",""),"-","")," ",""), 8) -> 92904044 | B3576: 92.904.044/0001-64 | C3576: CENTRO MEDICO E PRONTO SOCORRO ENTRE IJUIS LTDA | D3576: RIO GRANDE DO SUL | E3576: 18923.43 | F3576: 1
A3577: =LEFT(SUBSTITUTE(SUBSTITUTE(SUBSTITUTE(SUBSTITUTE(TRIM(B3577),".",""),"/",""),"-","")," ",""), 8) -> 92943901 | B3577: 92.943.901/0001-35 | C3577: FUNDACAO UNIVERSITARIA DE ENDOCRINOLOGIA E FERTILIDADE | D3577: RIO GRANDE DO SUL | E3577: 556543.51 | F3577: 1
A3578: =LEFT(SUBSTITUTE(SUBSTITUTE(SUBSTITUTE(SUBSTITUTE(TRIM(B3578),".",""),"/",""),"-","")," ",""), 8) -> 93316594 | B3578: 93.316.594/0001-25 | C3578: PREVENCOR ECO COLOR DOPPLER LTDA | D3578: RIO GRANDE DO SUL | E3578: 333667.53 | F3578: 1
A3579: =LEFT(SUBSTITUTE(SUBSTITUTE(SUBSTITUTE(SUBSTITUTE(TRIM(B3579),".",""),"/",""),"-","")," ",""), 8) -> 93664464 | B3579: 93.664.464/0001-83 | C3579: CENTRO CLINICO TRES FIGUEIRAS LTDA | D3579: RIO GRANDE DO SUL | E3579: 897558.28 | F3579: 1
A3580: =LEFT(SUBSTITUTE(SUBSTITUTE(SUBSTITUTE(SUBSTITUTE(TRIM(B3580),".",""),"/",""),"-","")," ",""), 8) -> 93850238 | B3580: 93.850.238/0002-78 | C3580: CLINICA MEDISINOS ESTEIO LTDA | D3580: RIO GRANDE DO SUL | E3580: 146343.38 | F3580: 1
A3581: =LEFT(SUBSTITUTE(SUBSTITUTE(SUBSTITUTE(SUBSTITUTE(TRIM(B3581),".",""),"/",""),"-","")," ",""), 8) -> 93850238 | B3581: 93.850.238/0003-59 | C3581: CLINICA MEDISINOS ESTEIO LTDA | D3581: RIO GRANDE DO SUL | E3581: 14829.93 | F3581: 1
A3582: =LEFT(SUBSTITUTE(SUBSTITUTE(SUBSTITUTE(SUBSTITUTE(TRIM(B3582),".",""),"/",""),"-","")," ",""), 8) -> 94449907 | B3582: 94.449.907/0001-86 | C3582: ASSOCIACAO HOSPITALAR CHIAPETTA | D3582: RIO GRANDE DO SUL | E3582: 762253.82 | F3582: 1
A3583: =LEFT(SUBSTITUTE(SUBSTITUTE(SUBSTITUTE(SUBSTITUTE(TRIM(B3583),".",""),"/",""),"-","")," ",""), 8) -> 94757986 | B3583: 94.757.986/0001-92 | C3583: FUNDACAO HOSPITAL DE CARIDADE DE QUARAI | D3583: RIO GRANDE DO SUL | E3583: 25266801 | F3583: 1
... A3640: =LEFT(SUBSTITUTE(SUBSTITUTE(SUBSTITUTE(SUBSTITUTE(TRIM(B3640),".",""),"/",""),"-","")," ",""), 8) -> 98673882 | B3640: 98.673.882/0001-50 | C3640: HOSPITAL BENEFICIENTE NOSSA SENHORA DA SAUDE | D3640: RIO GRANDE DO SUL | E3640: 1529405.2 | F3640: 1

Sheet SCRIPT_PYTHON
